micropython_eliza/__init__.py
micropython_eliza/chat.py
micropython_eliza/demo.py
micropython_eliza/session.py
micropython_eliza/identities/__init__.py
micropython_eliza/identities/eliza.py
micropython_eliza/identities/eliza_demo.py
micropython_eliza-0.1.1.dist-info/METADATA
micropython_eliza-0.1.1.dist-info/WHEEL
micropython_eliza-0.1.1.dist-info/licenses/LICENSE
micropython_eliza-0.1.1.dist-info/RECORD
