Metadata-Version: 2.1
Name: micropython-eliza
Version: 0.1.1
Summary: ELIZA chatbot for MicroPython. Based on 'ELIZA' by Joseph Weizenbaum, 1966.
Project-URL: GitHub, https://github.com/denise-pl/micropython-ELIZA
Project-URL: Demo, https://www.szymonjessa.com/eliza
Author-email: Szymon Jessa <szymon.coding@gmail.com>
License-File: LICENSE
Keywords: ELIZA,ai,chatbot,micropython,nlp
Classifier: License :: OSI Approved :: BSD License
Classifier: Natural Language :: English
Classifier: Operating System :: OS Independent
Classifier: Programming Language :: Python :: 3
Classifier: Programming Language :: Python :: Implementation :: MicroPython
Classifier: Topic :: Communications :: Chat
Classifier: Topic :: Scientific/Engineering :: Artificial Intelligence
Requires-Python: >=3.8
